tinkerforge2mqtt/__init__.py
tinkerforge2mqtt/__main__.py
tinkerforge2mqtt/constants.py
tinkerforge2mqtt/user_settings.py
tinkerforge2mqtt/cli_app/__init__.py
tinkerforge2mqtt/cli_app/discovering.py
tinkerforge2mqtt/cli_app/publish.py
tinkerforge2mqtt/cli_app/settings.py
tinkerforge2mqtt/cli_app/systemd.py
tinkerforge2mqtt/cli_app/update_readme_history.py
tinkerforge2mqtt/cli_dev/__init__.py
tinkerforge2mqtt/cli_dev/code_style.py
tinkerforge2mqtt/cli_dev/packaging.py
tinkerforge2mqtt/cli_dev/testing.py
tinkerforge2mqtt/device_map/__init__.py
tinkerforge2mqtt/device_map/brick_hat_zero.py
tinkerforge2mqtt/device_map/bricklet_analog_in_v3.py
tinkerforge2mqtt/device_map/bricklet_humidity_v2.py
tinkerforge2mqtt/device_map/bricklet_industrial_dual_relay.py
tinkerforge2mqtt/device_map/bricklet_motion_detector_v2.py
tinkerforge2mqtt/device_map/bricklet_solid_state_relay_v2.py
tinkerforge2mqtt/device_map/bricklet_temperature_v2.py
tinkerforge2mqtt/device_map/bricklet_voltage_current_v2.py
tinkerforge2mqtt/device_map_utils/__init__.py
tinkerforge2mqtt/device_map_utils/base.py
tinkerforge2mqtt/device_map_utils/generics.py
tinkerforge2mqtt/device_map_utils/led_config.py
tinkerforge2mqtt/device_map_utils/utils.py
tinkerforge2mqtt/device_registry/__init__.py
tinkerforge2mqtt/device_registry/devices_handler.py
tinkerforge2mqtt/tests/__init__.py
tinkerforge2mqtt/tests/test_doctests.py
tinkerforge2mqtt/tests/test_project_setup.py
tinkerforge2mqtt/utilities/__init__.py
tinkerforge2mqtt/utilities/dew_point.py
tinkerforge2mqtt-0.9.1.dist-info/METADATA
tinkerforge2mqtt-0.9.1.dist-info/WHEEL
tinkerforge2mqtt-0.9.1.dist-info/entry_points.txt
tinkerforge2mqtt-0.9.1.dist-info/top_level.txt
tinkerforge2mqtt-0.9.1.dist-info/RECORD
