Metadata-Version: 2.1
Name: tinkerforge2mqtt
Version: 0.9.1
Summary: Emit MQTT events from Tinkerforge devices
Author-email: Jens Diemer <git@jensdiemer.de>
License: GPL-3.0-or-later
Project-URL: Documentation, https://github.com/jedie/tinkerforge2mqtt
Project-URL: Source, https://github.com/jedie/tinkerforge2mqtt
Requires-Python: >=3.10
Requires-Dist: tinkerforge
Requires-Dist: ha-services >=2.5.0
Requires-Dist: cli-base-utilities
Requires-Dist: bx-py-utils
Requires-Dist: click
Requires-Dist: rich-click
Requires-Dist: rich
Provides-Extra: dev
Requires-Dist: manageprojects ; extra == 'dev'
Requires-Dist: urllib3 ; extra == 'dev'
Requires-Dist: pip-tools ; extra == 'dev'
Requires-Dist: tox ; extra == 'dev'
Requires-Dist: coverage ; extra == 'dev'
Requires-Dist: autopep8 ; extra == 'dev'
Requires-Dist: pyupgrade ; extra == 'dev'
Requires-Dist: flake8 ; extra == 'dev'
Requires-Dist: flake8-bugbear ; extra == 'dev'
Requires-Dist: pyflakes ; extra == 'dev'
Requires-Dist: codespell ; extra == 'dev'
Requires-Dist: EditorConfig ; extra == 'dev'
Requires-Dist: safety ; extra == 'dev'
Requires-Dist: mypy ; extra == 'dev'
Requires-Dist: twine ; extra == 'dev'
Requires-Dist: typeguard ; extra == 'dev'
Requires-Dist: darker[color,flynt,isort] ; extra == 'dev'
Requires-Dist: tomli ; extra == 'dev'
